<?xml version="1.0" encoding="UTF-8"?>
<!DOCTYPE mapper PUBLIC "-//mybatis.org//DTD Mapper 3.0//EN" "http://mybatis.org/dtd/mybatis-3-mapper.dtd">
<mapper namespace="com.keji.blog.dao.UpdateTimeLineDao">
  <resultMap id="BaseResultMap" type="com.keji.blog.dataobject.UpdateTimeLineDO">
    <id column="id" jdbcType="BIGINT" property="id" />
    <result column="title" jdbcType="VARCHAR" property="title" />
    <result column="content" jdbcType="VARCHAR" property="content" />
    <result column="gmt_create" jdbcType="TIMESTAMP" property="gmtCreate" />
    <result column="gmt_modified" jdbcType="TIMESTAMP" property="gmtModified" />
    <result column="status" jdbcType="INTEGER" property="status" />
    <result column="is_del" jdbcType="INTEGER" property="isDel" />
  </resultMap>

  <sql id="Base_Column_List">
    id, title, content, gmt_create, gmt_modified, status, is_del
  </sql>

  <select id="selectByPrimaryKey" parameterType="java.lang.Long" resultMap="BaseResultMap">
    select
    <include refid="Base_Column_List" />
    from update_time_line
    where id = #{id,jdbcType=BIGINT} and is_del = '0'
  </select>

  <select id="listAll" resultMap="BaseResultMap">
    select
    <include refid="Base_Column_List" />
    from update_time_line
    where is_del = '0'
  </select>

  <select id="selectDeleteByPk" parameterType="java.lang.Long" resultMap="BaseResultMap">
    select 
    <include refid="Base_Column_List" />
    from update_time_line
    where id = #{id,jdbcType=BIGINT} and is_del = '1'
  </select>

  <delete id="deleteByPrimaryKey" parameterType="java.lang.Long">
    delete from update_time_line
    where id = #{id,jdbcType=BIGINT}
  </delete>

  <insert id="insert" parameterType="com.keji.blog.dataobject.UpdateTimeLineDO">
    insert into update_time_line (id, title, content, 
      gmt_create, gmt_modified, status, 
      is_del)
    values (#{id,jdbcType=BIGINT}, #{title,jdbcType=VARCHAR}, #{content,jdbcType=VARCHAR}, 
      #{gmtCreate,jdbcType=TIMESTAMP}, #{gmtModified,jdbcType=TIMESTAMP}, #{status,jdbcType=INTEGER}, 
      #{isDel,jdbcType=INTEGER})
  </insert>

  <insert id="insertSelective" parameterType="com.keji.blog.dataobject.UpdateTimeLineDO">
    insert into update_time_line
    <trim prefix="(" suffix=")" suffixOverrides=",">
      <if test="id != null">
        id,
      </if>
      <if test="title != null">
        title,
      </if>
      <if test="content != null">
        content,
      </if>
      <if test="gmtCreate != null">
        gmt_create,
      </if>
      <if test="gmtModified != null">
        gmt_modified,
      </if>
      <if test="status != null">
        status,
      </if>
      <if test="isDel != null">
        is_del,
      </if>
    </trim>
    <trim prefix="values (" suffix=")" suffixOverrides=",">
      <if test="id != null">
        #{id,jdbcType=BIGINT},
      </if>
      <if test="title != null">
        #{title,jdbcType=VARCHAR},
      </if>
      <if test="content != null">
        #{content,jdbcType=VARCHAR},
      </if>
      <if test="gmtCreate != null">
        #{gmtCreate,jdbcType=TIMESTAMP},
      </if>
      <if test="gmtModified != null">
        #{gmtModified,jdbcType=TIMESTAMP},
      </if>
      <if test="status != null">
        #{status,jdbcType=INTEGER},
      </if>
      <if test="isDel != null">
        #{isDel,jdbcType=INTEGER},
      </if>
    </trim>
  </insert>

  <update id="updateByPrimaryKeySelective" parameterType="com.keji.blog.dataobject.UpdateTimeLineDO">
    update update_time_line
    <set>
      <if test="title != null">
        title = #{title,jdbcType=VARCHAR},
      </if>
      <if test="content != null">
        content = #{content,jdbcType=VARCHAR},
      </if>
      <if test="gmtCreate != null">
        gmt_create = #{gmtCreate,jdbcType=TIMESTAMP},
      </if>
      <if test="gmtModified != null">
        gmt_modified = #{gmtModified,jdbcType=TIMESTAMP},
      </if>
      <if test="status != null">
        status = #{status,jdbcType=INTEGER},
      </if>
      <if test="isDel != null">
        is_del = #{isDel,jdbcType=INTEGER},
      </if>
    </set>
    where id = #{id,jdbcType=BIGINT}
  </update>

  <update id="updateByPrimaryKey" parameterType="com.keji.blog.dataobject.UpdateTimeLineDO">
    update update_time_line
    set title = #{title,jdbcType=VARCHAR},
      content = #{content,jdbcType=VARCHAR},
      gmt_create = #{gmtCreate,jdbcType=TIMESTAMP},
      gmt_modified = #{gmtModified,jdbcType=TIMESTAMP},
      status = #{status,jdbcType=INTEGER},
      is_del = #{isDel,jdbcType=INTEGER}
    where id = #{id,jdbcType=BIGINT}
  </update>

</mapper>